resource_locator_program/app.py
resource_locator_program/path_teacher.py
resource_locator_program/resource_locator.py
resource_locator_program/setup_screen.py
resource_locator_program/shared_widgets.py
Resource_Locator_Program-0.0.3.dist-info/LICENSE
Resource_Locator_Program-0.0.3.dist-info/METADATA
Resource_Locator_Program-0.0.3.dist-info/WHEEL
Resource_Locator_Program-0.0.3.dist-info/entry_points.txt
Resource_Locator_Program-0.0.3.dist-info/top_level.txt
Resource_Locator_Program-0.0.3.dist-info/RECORD
