Metadata-Version: 2.1
Name: Resource-Locator-Program
Version: 0.0.3
Summary: Resource Locator Program
Home-page: https://www.github.com/pylabrobot/resource-locator-program/
Author: Rick Wierenga
Author-email: rick_wierenga@icloud.com
License-File: LICENSE
Requires-Dist: PyQt6
Requires-Dist: pylabrobot
